MANIFEST.in
README.md
lws.bycython.cpp
lws.pyx
lwslib.pxd
setup.py
lws.egg-info/PKG-INFO
lws.egg-info/SOURCES.txt
lws.egg-info/dependency_links.txt
lws.egg-info/requires.txt
lws.egg-info/top_level.txt
lwslib/lwslib.cpp
lwslib/lwslib.h