Metadata-Version: 2.1
Name: lws
Version: 1.2.7
Summary: Fast spectrogram phase reconstruction using Local Weighted Sums
Home-page: https://github.com/Jonathan-LeRoux/lws
Author: Jonathan Le Roux
Author-email: leroux@merl.com
License: Apache 2.0
Download-URL: https://github.com/Jonathan-LeRoux/lws/archive/1.2.7.tar.gz
Keywords: phase,reconstruction,stft,short-term Fourier Transform,spectrogram
Platform: UNKNOWN
Classifier: Programming Language :: Python
Classifier: Intended Audience :: Developers
Classifier: Topic :: Multimedia :: Sound/Audio :: Analysis
Classifier: Programming Language :: Python :: 2
Classifier: Programming Language :: Python :: 2.7
Classifier: Programming Language :: Python :: 3
Classifier: Programming Language :: Python :: 3.5
Classifier: Programming Language :: Python :: 3.6
Classifier: Programming Language :: Python :: 3.7
